{
 "name": "Biscogniauxia",
 "zhtw": "炭皮菌屬",
 "zhcn": "炭皮菌属",
 "timestamp": "20260719-094145",
 "list": [
  {
   "name": "Biscogniauxia uniapiculata",
   "zhtw": "附胞炭皮菌",
   "zhcn": "附胞炭皮菌",
   "img": "Biscogniauxia_nummularia_1_CC BY-NC_Hannah Wang.jpg"
  }
 ],
 "note": "炭皮菌屬隸屬子囊菌門糞殼菌綱（Sordariomycetes）炭角菌目（Xylariales）炭墊菌科（Graphostromataceae，舊置炭角菌科 Xylariaceae），為樹皮棲居的炭角菌類植物病原。子實體為廣鋪、扁平如殼痂的子座（stroma），黑色、碳質，常於寄主枝幹表皮下發育、成熟後使表皮成片剝落而露出（故名「炭皮」）。子座內埋生一層子囊殼（perithecium），各以小孔口開於表面；子囊具八孢，子囊孢子暗褐、單細胞、具縱向萌發縫。生態上為弱寄生兼潛伏病原，於寄主受逆境（乾旱等）時轉為侵染性，引起木本植物的炭色潰瘍與枝枯。代表種如錢斑炭皮菌（Biscogniauxia nummularia，櫸樹病原）與地中海炭皮菌（B. mediterranea，櫟炭色潰瘍病）。本屬以黑色殼痂狀子座著稱。"
}