{
 "name": "Stemonitis",
 "zhtw": "髮網黏菌屬",
 "zhcn": "发网黏菌属",
 "timestamp": "20260110-095920",
 "list": [
  {
   "name": "Stemonitis axifera",
   "zhtw": "光孢髮網黏菌",
   "zhcn": "光孢发网黏菌",
   "img": "Stemonitis_axifera_1_CC BY-NC_陳雅芬.jpg"
  },
  {
   "name": "Stemonitis axifera var. smithii",
   "zhtw": "光孢髮網黏菌亞小變種",
   "zhcn": "光孢发网黏菌亚小变种",
   "img": "Stemonitis_axifera var. smithii_1_CC BY-NC_柯文俊.jpg"
  },
  {
   "name": "Stemonitis flavogenita",
   "zhtw": "黃昉髮網黏菌",
   "zhcn": "黄昉发网黏菌",
   "img": "Stemonitis_flavogenita_1_CC BY-NC_陳雅芬.jpg"
  },
  {
   "name": "Stemonitis fusca",
   "zhtw": "褐髮網黏菌",
   "zhcn": "褐发网黏菌",
   "img": "Stemonitis_fusca_10_CC BY-NC_陳雅芬.jpg"
  },
  {
   "name": "Stemonitis herbatica",
   "zhtw": "草生髮網黏菌",
   "zhcn": "草生发网黏菌",
   "img": "Stemonitis_herbatica_35714af0-9ccd-11ee-98b4-157429614128_1.jpg"
  },
  {
   "name": "Stemonitis laxifila",
   "zhtw": "疏網目髮網黏菌",
   "zhcn": "疏网目发网黏菌",
   "img": "Stemonitis_laxifila_1_CC BY-NC_陳雅芬.jpg"
  },
  {
   "name": "Stemonitis lignicola",
   "zhtw": "木生髮網黏菌",
   "zhcn": "木生发网黏菌",
   "img": "Stemonitis_lignicola_1690d550-613b-11ef-be83-0d9da1f4363b_1.jpg"
  },
  {
   "name": "Stemonitis nigrescens",
   "zhtw": "黑柄髮網菌",
   "zhcn": "黑柄发网菌",
   "img": "Stemonitis_nigrescens_8abdff50-a88c-11ef-bdd8-cf4ce03db38d_1.jpg"
  },
  {
   "name": "Stemonitis pallida",
   "zhtw": "灰褐髮網黏菌",
   "zhcn": "灰褐发网黏菌",
   "img": "Stemonitis_pallida_1_CC BY-NC_陳雅芬.jpg"
  },
  {
   "name": "Stemonitis pallida var. rubescens",
   "zhtw": "灰褐髮網黏菌赭紅變種",
   "zhcn": "灰褐发网黏菌赭红变种",
   "img": "Stemonitis_pallida var. rubescens_558baeb0-897a-10d9-b41e-b34c0caf8ec6_1.jpg"
  },
  {
   "name": "Stemonitis smithii",
   "zhtw": "亞小髮網黏菌",
   "zhcn": "亚小发网黏菌",
   "current": "Stemonitis axifera var. smithii",
   "current_zhtw": "光孢髮網黏菌亞小變種",
   "current_zhcn": "光孢发网黏菌亚小变种",
   "img": "Stemonitis_axifera var. smithii_1_CC BY-NC_柯文俊.jpg"
  },
  {
   "name": "Stemonitis splendens",
   "zhtw": "美髮網黏菌",
   "zhcn": "美发网黏菌",
   "img": "Stemonitis_splendens_7ca30000-ea6f-11ed-8ed5-15dc0f6c60fa_1.jpg"
  }
 ]
}