{
 "name": "Galerina",
 "zhtw": "盔孢傘屬",
 "zhcn": "盔孢伞属",
 "timestamp": "20260719-094145",
 "list": [
  {
   "name": "Galerina helvoliceps",
   "zhtw": "黃褐盔孢傘",
   "zhcn": "黄褐盔孢伞",
   "img": "Galerina_helvoliceps_5_CC BY-NC_柯文俊.jpg"
  },
  {
   "name": "Galerina heterocystis",
   "zhtw": "異囊盔孢傘",
   "zhcn": "异囊盔孢伞",
   "img": "Galerina_heterocystis_3_CC BY-NC_陳雅芬.jpg"
  },
  {
   "name": "Galerina hypnorum",
   "zhtw": "苔蘚盔孢傘",
   "zhcn": "苔藓盔孢伞",
   "img": "Galerina_hypnorum_1_CC BY-NC_陳麗紅.jpg"
  },
  {
   "name": "Galerina marginata",
   "zhtw": "紋緣盔孢傘",
   "zhcn": "纹缘盔孢伞",
   "img": "Galerina_marginata_1_CC BY-NC_陳麗紅.jpg"
  },
  {
   "name": "Galerina papillata",
   "zhtw": "乳突盔孢傘",
   "zhcn": "乳突盔孢伞",
   "img": "Galerina_papillata_116ca7f0-3fda-11f1-92a7-41067c4fc4f6_1.jpg"
  },
  {
   "name": "Galerina patagonica",
   "zhtw": "巴塔哥尼亞盔孢傘",
   "zhcn": "巴塔哥尼亚盔孢伞",
   "img": "Galerina_patagonica_1_CC BY-NC_陳雅芬.jpg"
  },
  {
   "name": "Galerina sulciceps",
   "zhtw": "條蓋盔孢傘",
   "zhcn": "条盖盔孢伞",
   "img": "Galerina_sulciceps_d4d938f0-5b12-11f0-a588-6db7367c31f1_1.jpg"
  },
  {
   "name": "Galerina terrestris",
   "zhtw": "土棲盔孢傘",
   "zhcn": "土栖盔孢伞",
   "img": "Galerina_terrestris_5_CC BY-NC_柯文俊.jpg"
  }
 ],
 "note": "盔孢傘屬隸屬擔子菌門傘菌綱傘菌目層腹菌科（Hymenogastraceae，舊置絲膜菌科或球蓋菇科），逾三百種，世界廣布。子實體小型，菌蓋圓錐形至鐘形（狀如盔，故名「盔孢」），黃褐至蜜褐色、具吸水性，菌柄細而脆、常具不明顯菌環。菌褶直生至彎生，成熟呈鏽褐；擔孢子鏽褐、表面具疣或具凹點、常具盤狀芽孔，孢子印鏽褐。營腐生，多生於腐木上，地生者偏好苔蘚間。毒理意義極為重大：細環盔孢傘（Galerina marginata）等含致命的鵝膏毒肽（α-amanitin），與小型可食菇或致幻的裸蓋菇外形相似，曾造成致命誤食。本屬種類繁多、外形樸素，因含劇毒種而為採食小褐菇時最須警惕的類群之一。"
}