{
 "genus": "Leocarpus",
 "name": "fragilis",
 "date": [
  "08/18/2024,7875177825925913"
 ],
 "names_zhtw": [
  "光果黏菌"
 ],
 "names_en": [],
 "url": "7875177825925913",
 "images": [
  {
   "author": "林慧美",
   "image_src": "Leocarpus_fragilis_982ba3f0-8916-10f8-9e63-2fd2d82380ae_1.jpg"
  },
  {
   "author": "林慧美",
   "image_src": "Leocarpus_fragilis_982ba3f0-8916-10f8-9e63-2fd2d82380ae_2.jpg"
  }
 ],
 "names_zhcn": [
  "光果黏菌"
 ],
 "meta": {
  "CapColors": "4294901760",
  "CapDiamRangeValues": "",
  "CapShape": "",
  "CapTexture": "",
  "CapMargin": "",
  "HymeniumType": "",
  "HymeniumColors": "",
  "HymeniumSporePrints": "",
  "HymeniumGillArrangement": "",
  "HymeniumGillAttachment": "",
  "HymeniumGillMarginate": "",
  "HymeniumPoresPerMM": "",
  "StalkAttachment": "",
  "StalkColors": "",
  "StalkTexture": "",
  "StalkHollow": "",
  "StalkPartialVeil": "",
  "StalkVolva": "",
  "StalkBase": "",
  "StalkDiamRangeValuess": "",
  "StalkLengthRangeValuess": "",
  "HeightRangeValuess": "",
  "Rareness": "",
  "Seasons": "",
  "GrowthType": "",
  "GrowthEnv": "wood",
  "Bruising": "",
  "Bioluminescent": "",
  "Edible": "",
  "Smell": "",
  "Taste": "",
  "LookAlikes": "",
  "Note": "台灣高海拔拍攝記錄。"
 },
 "inaturalist": [
  {
   "name": "Leocarpus fragilis",
   "cname": "Insect-egg Slime",
   "url": "https://www.inaturalist.org/taxa/56273-Leocarpus-fragilis",
   "src": "https://inaturalist-open-data.s3.amazonaws.com/photos/251110640/thumb.jpg"
  },
  {
   "name": "Leocarpus fragilis fragilis",
   "cname": "",
   "url": "https://www.inaturalist.org/taxa/602715-Leocarpus-fragilis-fragilis",
   "src": "https://inaturalist-open-data.s3.amazonaws.com/photos/16206041/thumb.jpg"
  },
  {
   "name": "Leocarpus fragilis var. bisporus",
   "cname": "",
   "url": "https://www.inaturalist.org/taxa/602714-Leocarpus-fragilis-bisporus",
   "src": ""
  }
 ],
 "timestamp": "20251207-163922"
}