{
 "genus": "Cerotelium",
 "name": "malvicola",
 "date": [
  "02/27/2026,25936854452664974"
 ],
 "names_zhtw": [
  "йҢҰи‘өйҠ№з—…иҸҢ"
 ],
 "names_en": [],
 "url": "25936854452664974",
 "images": [
  {
   "author": "йҷійә—зҙ…",
   "image_src": "Cerotelium_malvicola_59b8ed90-3fdd-11f1-92a7-41067c4fc4f6_1.jpg"
  },
  {
   "author": "йҷійә—зҙ…",
   "image_src": "Cerotelium_malvicola_59b8ed90-3fdd-11f1-92a7-41067c4fc4f6_2.jpg"
  },
  {
   "author": "йҷійә—зҙ…",
   "image_src": "Cerotelium_malvicola_59b8ed90-3fdd-11f1-92a7-41067c4fc4f6_3.jpg"
  },
  {
   "author": "йҷійә—зҙ…",
   "image_src": "Cerotelium_malvicola_59b8ed90-3fdd-11f1-92a7-41067c4fc4f6_4.jpg"
  },
  {
   "author": "йҷійә—зҙ…",
   "image_src": "Cerotelium_malvicola_59b8ed90-3fdd-11f1-92a7-41067c4fc4f6_5.jpg"
  },
  {
   "author": "йҷійә—зҙ…",
   "image_src": "Cerotelium_malvicola_59b8ed90-3fdd-11f1-92a7-41067c4fc4f6_6.jpg"
  },
  {
   "author": "йҷійә—зҙ…",
   "image_src": "Cerotelium_malvicola_59b8ed90-3fdd-11f1-92a7-41067c4fc4f6_7.jpg"
  },
  {
   "author": "йҷійә—зҙ…",
   "image_src": "Cerotelium_malvicola_59b8ed90-3fdd-11f1-92a7-41067c4fc4f6_8.jpg"
  },
  {
   "author": "йҷійә—зҙ…",
   "image_src": "Cerotelium_malvicola_59b8ed90-3fdd-11f1-92a7-41067c4fc4f6_9.jpg"
  }
 ],
 "names_zhcn": [
  "й”Ұи‘өй”Ҳз—…иҸҢ"
 ],
 "meta": {
  "CapColors": "4294083840",
  "CapDiamRangeValues": "",
  "CapShape": "",
  "CapTexture": "",
  "CapMargin": "",
  "HymeniumType": "",
  "HymeniumColors": "",
  "HymeniumSporePrints": "",
  "HymeniumGillArrangement": "",
  "HymeniumGillAttachment": "",
  "HymeniumGillMarginate": "",
  "HymeniumPoresPerMM": "",
  "StalkAttachment": "",
  "StalkColors": "",
  "StalkTexture": "",
  "StalkHollow": "",
  "StalkPartialVeil": "",
  "StalkVolva": "",
  "StalkBase": "",
  "StalkDiamRangeValuess": "",
  "StalkLengthRangeValuess": "",
  "HeightRangeValuess": "",
  "Rareness": "",
  "Seasons": "",
  "GrowthType": "",
  "GrowthEnv": "leaves,parasitic",
  "Bruising": "",
  "Bioluminescent": "",
  "Edible": "",
  "Smell": "",
  "Taste": "",
  "LookAlikes": "",
  "Note": ""
 },
 "timestamp": "20260425-104540"
}