{
 "name": "Plicatura",
 "zhtw": "褶尾菌屬",
 "zhcn": "褶尾菌属",
 "timestamp": "20260719-180210",
 "list": [
  {
   "name": "Plicatura crispa",
   "zhtw": "皺波褶尾菌",
   "zhcn": "皱波褶尾菌",
   "current": "Plicaturopsis crispa",
   "current_zhtw": "皺波擬褶尾菌",
   "current_zhcn": "皱波拟褶尾菌",
   "img": "Plicatura_crispa_1_CC BY-NC_陳麗紅.jpg"
  }
 ],
 "note": "褶尾菌屬隸屬擔子菌門傘菌綱傘菌目（粉殼菌科 Amylocorticiaceae 一系）。子實體小型，側生於基質，無柄或具極短的側柄，菌蓋扇形、貝殼狀，薄而柔韌，表面被細絨毛、具同心環紋，白色至乳白、淡褐。最具特徵者為其子實層體：由低矮、分叉、彎曲且互相連結的脈狀褶皺（呈摺褶狀、近迷脈狀，故名「褶尾菌」）構成，介於菌褶與平滑面之間。擔孢子無色、光滑、臘腸形（彎曲）、非類澱粉，孢子印白色。營腐生，木生，多生於闊葉樹（尤樺、榛）的枯枝、倒木上，引起白色腐朽，常成群覆瓦狀疊生。代表種如雪白褶尾菌（Plicatura nivea）與皺褶尾菌（P. crispa／Plicaturopsis crispa）。本屬以薄韌、被毛的側生菌蓋與摺褶狀的子實層面界定，為枯枝上常見的小型木生真菌。"
}