{
 "genus": "Omphalotus",
 "name": "japonicus",
 "date": [
  "01/05/2025,8799588686818151",
  "11/12/2024,8499478436829179",
  "08/05/2024,8338311849612506",
  "04/27/2024,7293482807428754",
  "03/31/2024,7161397993970570",
  "01/24/2024,6904545319655840",
  "11/19/2023,6654811074629267",
  "11/10/2023,6624543704322671",
  "12/11/2022,5495156520594734",
  "11/19/2022,5433202116790175",
  "11/11/2022,5404421789668208",
  "10/26/2022,5362339453876442",
  "12/12/2021,4413900928720304",
  "11/29/2021,4369062643204133",
  "11/07/2021,4298779776899087",
  "03/27/2021,3630146540429084",
  "11/21/2020,3302276146549460",
  "10/28/2020,3238727422904333",
  "12/06/2018,1835153856595037",
  "11/26/2017,1379273608849733"
 ],
 "names_zhtw": [
  "日本臍菇"
 ],
 "names_en": [],
 "url": "3630146540429084",
 "images": [
  {
   "author": "李景泰",
   "image_src": "Omphalotus_japonicus_1_CC BY-NC_李景泰.jpg"
  },
  {
   "author": "Hannah Wang",
   "image_src": "Omphalotus_japonicus_3_CC BY-NC_Hannah Wang.jpg"
  },
  {
   "author": "Hannah Wang",
   "image_src": "Omphalotus_japonicus_5_CC BY-NC_Hannah Wang.jpg"
  },
  {
   "author": "向高世",
   "image_src": "Omphalotus_Japonicus_19_CC BY-NC_向高世.jpg"
  },
  {
   "author": "陳麗紅",
   "image_src": "Omphalotus_japonicus_1_CC BY-NC_陳麗紅.jpg"
  },
  {
   "author": "陳麗紅",
   "image_src": "Omphalotus_japonicus_2_CC BY-NC_陳麗紅.jpg"
  },
  {
   "author": "陳麗紅",
   "image_src": "Omphalotus_japonicus_3_CC BY-NC_陳麗紅.jpg"
  },
  {
   "author": "陳麗紅",
   "image_src": "Omphalotus_japonicus_4_CC BY-NC_陳麗紅.jpg"
  },
  {
   "author": "陳麗紅",
   "image_src": "Omphalotus_japonicus_5_CC BY-NC_陳麗紅.jpg"
  },
  {
   "author": "陳麗紅",
   "image_src": "Omphalotus_japonicus_6_CC BY-NC_陳麗紅.jpg"
  },
  {
   "author": "陳麗紅",
   "image_src": "Omphalotus_japonicus_7_CC BY-NC_陳麗紅.jpg"
  },
  {
   "author": "陳麗紅",
   "image_src": "Omphalotus_japonicus_8_CC BY-NC_陳麗紅.jpg"
  },
  {
   "author": "陳麗紅",
   "image_src": "Omphalotus_japonicus_9_CC BY-NC_陳麗紅.jpg"
  },
  {
   "author": "陳麗紅",
   "image_src": "Omphalotus_japonicus_10_CC BY-NC_陳麗紅.jpg"
  },
  {
   "author": "陳麗紅",
   "image_src": "Omphalotus_japonicus_11_CC BY-NC_陳麗紅.jpg"
  },
  {
   "author": "陳麗紅",
   "image_src": "Omphalotus_japonicus_12_CC BY-NC_陳麗紅.jpg"
  },
  {
   "author": "陳麗紅",
   "image_src": "Omphalotus_japonicus_13_CC BY-NC_陳麗紅.jpg"
  },
  {
   "author": "陳麗紅",
   "image_src": "Omphalotus_japonicus_14_CC BY-NC_陳麗紅.jpg"
  },
  {
   "author": "陳麗紅",
   "image_src": "Omphalotus_japonicus_15_CC BY-NC_陳麗紅.jpg"
  },
  {
   "author": "陳麗紅",
   "image_src": "Omphalotus_japonicus_16_CC BY-NC_陳麗紅.jpg"
  },
  {
   "author": "Hannah Wang",
   "image_src": "Omphalotus_japonicus_1_CC BY-NC_Hannah Wang.jpg"
  },
  {
   "author": "Hannah Wang",
   "image_src": "Omphalotus_japonicus_2_CC BY-NC_Hannah Wang.jpg"
  },
  {
   "author": "Hannah Wang",
   "image_src": "Omphalotus_japonicus_6_CC BY-NC_Hannah Wang.jpg"
  },
  {
   "author": "Hannah Wang",
   "image_src": "Omphalotus_japonicus_7_CC BY-NC_Hannah Wang.jpg"
  },
  {
   "author": "Hannah Wang",
   "image_src": "Omphalotus_japonicus_8_CC BY-NC_Hannah Wang.jpg"
  },
  {
   "author": "Hannah Wang",
   "image_src": "Omphalotus_japonicus_9_CC BY-NC_Hannah Wang.jpg"
  },
  {
   "author": "Hannah Wang",
   "image_src": "Omphalotus_japonicus_10_CC BY-NC_Hannah Wang.jpg"
  },
  {
   "author": "Hannah Wang",
   "image_src": "Omphalotus_japonicus_11_CC BY-NC_Hannah Wang.jpg"
  },
  {
   "author": "Hannah Wang",
   "image_src": "Omphalotus_japonicus_12_CC BY-NC_Hannah Wang.jpg"
  },
  {
   "author": "Hannah Wang",
   "image_src": "Omphalotus_japonicus_13_CC BY-NC_Hannah Wang.jpg"
  },
  {
   "author": "游婉婷",
   "image_src": "Omphalotus_Japonicus_15_CC BY-NC_游婉婷.jpg"
  },
  {
   "author": "游婉婷",
   "image_src": "Omphalotus_Japonicus_2_CC BY-NC_游婉婷.jpg"
  },
  {
   "author": "游婉婷",
   "image_src": "Omphalotus_Japonicus_3_CC BY-NC_游婉婷.jpg"
  },
  {
   "author": "游婉婷",
   "image_src": "Omphalotus_Japonicus_4_CC BY-NC_游婉婷.jpg"
  },
  {
   "author": "游婉婷",
   "image_src": "Omphalotus_Japonicus_5_CC BY-NC_游婉婷.jpg"
  },
  {
   "author": "游婉婷",
   "image_src": "Omphalotus_Japonicus_6_CC BY-NC_游婉婷.jpg"
  },
  {
   "author": "游婉婷",
   "image_src": "Omphalotus_Japonicus_7_CC BY-NC_游婉婷.jpg"
  },
  {
   "author": "柯文俊",
   "image_src": "Omphalotus_Japonicus_8_CC BY-NC_柯文俊.jpg"
  },
  {
   "author": "柯文俊",
   "image_src": "Omphalotus_Japonicus_9_CC BY-NC_柯文俊.jpg"
  },
  {
   "author": "柯文俊",
   "image_src": "Omphalotus_Japonicus_10_CC BY-NC_柯文俊.jpg"
  },
  {
   "author": "柯文俊",
   "image_src": "Omphalotus_Japonicus_11_CC BY-NC_柯文俊.jpg"
  },
  {
   "author": "柯文俊",
   "image_src": "Omphalotus_Japonicus_12_CC BY-NC_柯文俊.jpg"
  },
  {
   "author": "柯文俊",
   "image_src": "Omphalotus_Japonicus_13_CC BY-NC_柯文俊.jpg"
  },
  {
   "author": "游婉婷",
   "image_src": "Omphalotus_Japonicus_14_CC BY-NC_游婉婷.jpg"
  },
  {
   "author": "游婉婷",
   "image_src": "Omphalotus_Japonicus_1_CC BY-NC_游婉婷.jpg"
  },
  {
   "author": "游婉婷",
   "image_src": "Omphalotus_Japonicus_16_CC BY-NC_游婉婷.jpg"
  },
  {
   "author": "Hua-Te Fang",
   "image_src": "Omphalotus_Japonicus_17_CC BY-NC_Hua-Te Fang.jpg"
  },
  {
   "author": "Hua-Te Fang",
   "image_src": "Omphalotus_Japonicus_18_CC BY-NC_Hua-Te Fang.jpg"
  },
  {
   "author": "姜淋友",
   "image_src": "Omphalotus_japonicus_c9840d90-8742-11ee-8c17-7b36dbfd7c3f_1.jpg"
  },
  {
   "author": "姜淋友",
   "image_src": "Omphalotus_japonicus_c9840d90-8742-11ee-8c17-7b36dbfd7c3f_2.jpg"
  },
  {
   "author": "姜淋友",
   "image_src": "Omphalotus_japonicus_c9840d90-8742-11ee-8c17-7b36dbfd7c3f_3.jpg"
  },
  {
   "author": "吳湯姆",
   "image_src": "Omphalotus_japonicus_84acef20-bcc1-11ee-8a51-6b4eade79a79_1.jpg"
  },
  {
   "author": "吳湯姆",
   "image_src": "Omphalotus_japonicus_84acef20-bcc1-11ee-8a51-6b4eade79a79_2.jpg"
  },
  {
   "author": "吳湯姆",
   "image_src": "Omphalotus_japonicus_84acef20-bcc1-11ee-8a51-6b4eade79a79_3.jpg"
  },
  {
   "author": "吳湯姆",
   "image_src": "Omphalotus_japonicus_84acef20-bcc1-11ee-8a51-6b4eade79a79_4.jpg"
  },
  {
   "author": "吳湯姆",
   "image_src": "Omphalotus_japonicus_84acef20-bcc1-11ee-8a51-6b4eade79a79_5.jpg"
  },
  {
   "author": "蔡古媧",
   "image_src": "Omphalotus_japonicus_76821170-0792-11ef-89f3-6f850d94bc54_1.jpg"
  },
  {
   "author": "蔡古媧",
   "image_src": "Omphalotus_japonicus_76821170-0792-11ef-89f3-6f850d94bc54_2.jpg"
  },
  {
   "author": "蔡古媧",
   "image_src": "Omphalotus_japonicus_76821170-0792-11ef-89f3-6f850d94bc54_3.jpg"
  },
  {
   "author": "蔡古媧",
   "image_src": "Omphalotus_japonicus_76821170-0792-11ef-89f3-6f850d94bc54_4.jpg"
  },
  {
   "author": "蔡古媧",
   "image_src": "Omphalotus_japonicus_76821170-0792-11ef-89f3-6f850d94bc54_5.jpg"
  },
  {
   "author": "蔡古媧",
   "image_src": "Omphalotus_japonicus_76821170-0792-11ef-89f3-6f850d94bc54_6.jpg"
  },
  {
   "author": "蔡古媧",
   "image_src": "Omphalotus_japonicus_76821170-0792-11ef-89f3-6f850d94bc54_7.jpg"
  },
  {
   "author": "蔡古媧",
   "image_src": "Omphalotus_japonicus_76821170-0792-11ef-89f3-6f850d94bc54_8.jpg"
  },
  {
   "author": "蔡古媧",
   "image_src": "Omphalotus_japonicus_76821170-0792-11ef-89f3-6f850d94bc54_9.jpg"
  },
  {
   "author": "蔡古媧",
   "image_src": "Omphalotus_japonicus_d924ac00-8e03-11ef-a344-c1124aebf46c_1.jpg"
  },
  {
   "author": "蔡古媧",
   "image_src": "Omphalotus_japonicus_d924ac00-8e03-11ef-a344-c1124aebf46c_2.jpg"
  },
  {
   "author": "蔡古媧",
   "image_src": "Omphalotus_japonicus_d924ac00-8e03-11ef-a344-c1124aebf46c_3.jpg"
  },
  {
   "author": "蔡古媧",
   "image_src": "Omphalotus_japonicus_d924ac00-8e03-11ef-a344-c1124aebf46c_4.jpg"
  },
  {
   "author": "蔡古媧",
   "image_src": "Omphalotus_japonicus_d924ac00-8e03-11ef-a344-c1124aebf46c_5.jpg"
  },
  {
   "author": "吳湯姆",
   "image_src": "Omphalotus_japonicus_406f4d70-a14b-11ef-8c3e-692206fb761f_1.jpg"
  },
  {
   "author": "吳湯姆",
   "image_src": "Omphalotus_japonicus_406f4d70-a14b-11ef-8c3e-692206fb761f_2.jpg"
  },
  {
   "author": "吳湯姆",
   "image_src": "Omphalotus_japonicus_406f4d70-a14b-11ef-8c3e-692206fb761f_3.jpg"
  },
  {
   "author": "吳湯姆",
   "image_src": "Omphalotus_japonicus_406f4d70-a14b-11ef-8c3e-692206fb761f_4.jpg"
  },
  {
   "author": "吳湯姆",
   "image_src": "Omphalotus_japonicus_406f4d70-a14b-11ef-8c3e-692206fb761f_5.jpg"
  },
  {
   "author": "吳湯姆",
   "image_src": "Omphalotus_japonicus_406f4d70-a14b-11ef-8c3e-692206fb761f_6.jpg"
  },
  {
   "author": "吳湯姆",
   "image_src": "Omphalotus_japonicus_406f4d70-a14b-11ef-8c3e-692206fb761f_7.jpg"
  },
  {
   "author": "吳湯姆",
   "image_src": "Omphalotus_japonicus_b1de19c0-cb5b-11ef-abee-cd2091362276_1.jpg"
  },
  {
   "author": "吳湯姆",
   "image_src": "Omphalotus_japonicus_b1de19c0-cb5b-11ef-abee-cd2091362276_2.jpg"
  },
  {
   "author": "吳湯姆",
   "image_src": "Omphalotus_japonicus_b1de19c0-cb5b-11ef-abee-cd2091362276_3.jpg"
  },
  {
   "author": "吳湯姆",
   "image_src": "Omphalotus_japonicus_b1de19c0-cb5b-11ef-abee-cd2091362276_4.jpg"
  },
  {
   "author": "吳湯姆",
   "image_src": "Omphalotus_japonicus_b1de19c0-cb5b-11ef-abee-cd2091362276_5.jpg"
  },
  {
   "author": "吳湯姆",
   "image_src": "Omphalotus_japonicus_b1de19c0-cb5b-11ef-abee-cd2091362276_6.jpg"
  },
  {
   "author": "吳湯姆",
   "image_src": "Omphalotus_japonicus_b1de19c0-cb5b-11ef-abee-cd2091362276_7.jpg"
  },
  {
   "author": "吳湯姆",
   "image_src": "Omphalotus_japonicus_b1de19c0-cb5b-11ef-abee-cd2091362276_8.jpg"
  },
  {
   "author": "吳湯姆",
   "image_src": "Omphalotus_japonicus_b1de19c0-cb5b-11ef-abee-cd2091362276_9.jpg"
  },
  {
   "author": "吳湯姆",
   "image_src": "Omphalotus_japonicus_b1de19c0-cb5b-11ef-abee-cd2091362276_10.jpg"
  },
  {
   "author": "吳湯姆",
   "image_src": "Omphalotus_japonicus_b1de19c0-cb5b-11ef-abee-cd2091362276_11.jpg"
  },
  {
   "author": "吳湯姆",
   "image_src": "Omphalotus_japonicus_b1de19c0-cb5b-11ef-abee-cd2091362276_12.jpg"
  }
 ],
 "names_zhcn": [
  "日本脐菇"
 ],
 "meta": {
  "CapColors": "4286578816,4294901760,4286141768",
  "CapDiamRangeValues": "",
  "CapShape": "",
  "CapTexture": "",
  "CapMargin": "",
  "HymeniumType": "",
  "HymeniumColors": "",
  "HymeniumSporePrints": "",
  "HymeniumGillArrangement": "",
  "HymeniumGillAttachment": "",
  "HymeniumGillMarginate": "",
  "HymeniumPoresPerMM": "",
  "StalkAttachment": "",
  "StalkColors": "",
  "StalkTexture": "",
  "StalkHollow": "",
  "StalkPartialVeil": "",
  "StalkVolva": "",
  "StalkBase": "",
  "StalkDiamRangeValuess": "",
  "StalkLengthRangeValuess": "",
  "HeightRangeValuess": "",
  "Rareness": "",
  "Seasons": "autumn,winter",
  "GrowthType": "",
  "GrowthEnv": "wood",
  "Bruising": "",
  "Bioluminescent": "strong",
  "Edible": "toxic",
  "Smell": "",
  "Taste": "",
  "LookAlikes": "",
  "Note": "秋冬時節生長於台灣北部中海拔山毛櫸枯幹上。",
  "GrowthEco": "saprotrophic"
 },
 "inaturalist": [
  {
   "name": "Omphalotus japonicus",
   "cname": "Tsukiyotake",
   "url": "https://www.inaturalist.org/taxa/552696-Omphalotus-japonicus",
   "src": "https://inaturalist-open-data.s3.amazonaws.com/photos/249022786/thumb.jpg"
  }
 ],
 "timestamp": "20250202-163046"
}