{
 "name": "Vararia",
 "zhtw": "絲革菌屬",
 "zhcn": "丝革菌属",
 "timestamp": "20260719-094145",
 "list": [
  {
   "name": "Vararia investiens",
   "zhtw": "硬叉絲革菌",
   "zhcn": "硬叉丝革菌",
   "img": "Vararia_investiens_1_CC BY-NC_陳雅芬.jpg"
  }
 ],
 "note": "絲革菌屬隸屬擔子菌門傘菌綱紅菇目（Russulales）毛革菌科（Lachnocladiaceae），逾五十種，廣布，為平伏的革菌類（corticioid fungi）。子實體平伏（resupinate），薄、貼生於基質，膜質至革質，子實層面平滑至略具瘤突，白色、乳黃至赭褐。最重要的顯微鑑別特徵為其具發達的「雙叉分枝菌絲（dichophyses／dichohyphidia）」：一類厚壁、反覆作二叉分枝的束絲狀菌絲，交織於子實層中（故名「絲革菌」），為界定本屬的關鍵。擔孢子無色、光滑或具細刺、且呈類澱粉反應（amyloid，紅菇目特徵）。營腐生，木生，貼生於闊葉樹與針葉樹的腐木、枯枝下側，引起白色腐朽。本屬與毛革菌屬（Lachnocladium）等同科，以其二叉分枝的厚壁菌絲與類澱粉孢子界定，為腐木下側常見的平伏革菌類群之一。"
}