{
 "genus": "Lachnum",
 "name": "oncospermatum",
 "date": [
  "02/10/2024,6963211813789190",
  "01/20/2024,6878332822277090",
  "01/16/2024,6864673040309735"
 ],
 "names_zhtw": [
  "瘤狀粒毛盤菌"
 ],
 "names_en": [],
 "url": "3396532280457179",
 "images": [
  {
   "author": "陳雅芬",
   "image_src": "Lachnum_oncospermatum_1_CC BY-NC_陳雅芬.jpg"
  },
  {
   "author": "陳雅芬",
   "image_src": "Lachnum_oncospermatum_2_CC BY-NC_陳雅芬.jpg"
  },
  {
   "author": "陳雅芬",
   "image_src": "Lachnum_oncospermatum_3_CC BY-NC_陳雅芬.jpg"
  },
  {
   "author": "陳雅芬",
   "image_src": "Lachnum_oncospermatum_4_CC BY-NC_陳雅芬.jpg"
  },
  {
   "author": "陳雅芬",
   "image_src": "Lachnum_oncospermatum_5_CC BY-NC_陳雅芬.jpg"
  },
  {
   "author": "陳雅芬",
   "image_src": "Lachnum_oncospermatum_6_CC BY-NC_陳雅芬.jpg"
  },
  {
   "author": "陳雅芬",
   "image_src": "Lachnum_oncospermatum_7_CC BY-NC_陳雅芬.jpg"
  },
  {
   "author": "陳雅芬",
   "image_src": "Lachnum_oncospermatum_8_CC BY-NC_陳雅芬.jpg"
  },
  {
   "author": "陳雅芬",
   "image_src": "Lachnum_oncospermatum_9_CC BY-NC_陳雅芬.jpg"
  },
  {
   "author": "陳雅芬",
   "image_src": "Lachnum_oncospermatum_10_CC BY-NC_陳雅芬.jpg"
  },
  {
   "author": "姜淋友",
   "image_src": "Lachnum_oncospermatum_2dd1edb0-b5fd-11ee-8f2d-bb86bd516357_1.jpg"
  },
  {
   "author": "姜淋友",
   "image_src": "Lachnum_oncospermatum_2dd1edb0-b5fd-11ee-8f2d-bb86bd516357_2.jpg"
  },
  {
   "author": "姜淋友",
   "image_src": "Lachnum_oncospermatum_2dd1edb0-b5fd-11ee-8f2d-bb86bd516357_3.jpg"
  },
  {
   "author": "姜淋友",
   "image_src": "Lachnum_oncospermatum_2dd1edb0-b5fd-11ee-8f2d-bb86bd516357_4.jpg"
  },
  {
   "author": "江志緯",
   "image_src": "Lachnum_oncospermatum_6a8005e0-b791-11ee-b936-5db73244bf12_1.jpg"
  },
  {
   "author": "江志緯",
   "image_src": "Lachnum_oncospermatum_6a8005e0-b791-11ee-b936-5db73244bf12_2.jpg"
  },
  {
   "author": "江志緯",
   "image_src": "Lachnum_oncospermatum_6a8005e0-b791-11ee-b936-5db73244bf12_3.jpg"
  },
  {
   "author": "江志緯",
   "image_src": "Lachnum_oncospermatum_6a8005e0-b791-11ee-b936-5db73244bf12_4.jpg"
  },
  {
   "author": "江志緯",
   "image_src": "Lachnum_oncospermatum_6a8005e0-b791-11ee-b936-5db73244bf12_5.jpg"
  },
  {
   "author": "江志緯",
   "image_src": "Lachnum_oncospermatum_6a8005e0-b791-11ee-b936-5db73244bf12_6.jpg"
  },
  {
   "author": "江志緯",
   "image_src": "Lachnum_oncospermatum_6a8005e0-b791-11ee-b936-5db73244bf12_7.jpg"
  },
  {
   "author": "江志緯",
   "image_src": "Lachnum_oncospermatum_6a8005e0-b791-11ee-b936-5db73244bf12_8.jpg"
  },
  {
   "author": "江志緯",
   "image_src": "Lachnum_oncospermatum_6a8005e0-b791-11ee-b936-5db73244bf12_9.jpg"
  },
  {
   "author": "江志緯",
   "image_src": "Lachnum_oncospermatum_6a8005e0-b791-11ee-b936-5db73244bf12_10.jpg"
  },
  {
   "author": "江志緯",
   "image_src": "Lachnum_oncospermatum_6a8005e0-b791-11ee-b936-5db73244bf12_11.jpg"
  },
  {
   "author": "江志緯",
   "image_src": "Lachnum_oncospermatum_6a8005e0-b791-11ee-b936-5db73244bf12_12.jpg"
  },
  {
   "author": "江志緯",
   "image_src": "Lachnum_oncospermatum_6a8005e0-b791-11ee-b936-5db73244bf12_13.jpg"
  },
  {
   "author": "江志緯",
   "image_src": "Lachnum_oncospermatum_6a8005e0-b791-11ee-b936-5db73244bf12_14.jpg"
  },
  {
   "author": "江志緯",
   "image_src": "Lachnum_oncospermatum_6a8005e0-b791-11ee-b936-5db73244bf12_15.jpg"
  },
  {
   "author": "江志緯",
   "image_src": "Lachnum_oncospermatum_6a8005e0-b791-11ee-b936-5db73244bf12_16.jpg"
  },
  {
   "author": "陳雅芬",
   "image_src": "Lachnum_oncospermatum_1eee9870-c886-11ee-9b3e-95e26787b37f_1.jpg"
  },
  {
   "author": "陳雅芬",
   "image_src": "Lachnum_oncospermatum_1eee9870-c886-11ee-9b3e-95e26787b37f_2.jpg"
  }
 ],
 "names_zhcn": [
  "瘤状粒毛盘菌"
 ],
 "meta": {
  "CapColors": "4294956800",
  "CapDiamRangeValues": "",
  "CapShape": "",
  "CapTexture": "",
  "CapMargin": "",
  "HymeniumType": "",
  "HymeniumColors": "",
  "HymeniumSporePrints": "",
  "HymeniumGillArrangement": "",
  "HymeniumGillAttachment": "",
  "HymeniumGillMarginate": "",
  "HymeniumPoresPerMM": "",
  "StalkAttachment": "",
  "StalkColors": "",
  "StalkTexture": "",
  "StalkHollow": "",
  "StalkPartialVeil": "",
  "StalkVolva": "",
  "StalkBase": "",
  "StalkDiamRangeValuess": "",
  "StalkLengthRangeValuess": "",
  "Rareness": "",
  "Seasons": "",
  "GrowthType": "",
  "GrowthEnv": "wood",
  "Bruising": "",
  "Bioluminescent": "",
  "Edible": "",
  "Smell": "",
  "Taste": "",
  "LookAlikes": "",
  "Note": "",
  "GrowthEco": "saprotrophic"
 },
 "timestamp": "20241128-162702"
}