{
 "genus": "Conocybe",
 "name": "tenera",
 "date": [
  "10/14/2022"
 ],
 "names_zhtw": [
  "柔錐蓋傘"
 ],
 "names_en": [],
 "url": "5335005926609795",
 "images": [
  {
   "author": "陳麗紅",
   "image_src": "Conocybe_tenera_1_CC BY-NC_陳麗紅.jpg"
  },
  {
   "author": "陳麗紅",
   "image_src": "Conocybe_tenera_2_CC BY-NC_陳麗紅.jpg"
  },
  {
   "author": "陳麗紅",
   "image_src": "Conocybe_tenera_3_CC BY-NC_陳麗紅.jpg"
  },
  {
   "author": "陳麗紅",
   "image_src": "Conocybe_tenera_4_CC BY-NC_陳麗紅.jpg"
  },
  {
   "author": "陳麗紅",
   "image_src": "Conocybe_tenera_5_CC BY-NC_陳麗紅.jpg"
  },
  {
   "author": "陳麗紅",
   "image_src": "Conocybe_tenera_6_CC BY-NC_陳麗紅.jpg"
  },
  {
   "author": "陳麗紅",
   "image_src": "Conocybe_tenera_7_CC BY-NC_陳麗紅.jpg"
  },
  {
   "author": "陳麗紅",
   "image_src": "Conocybe_tenera_8_CC BY-NC_陳麗紅.jpg"
  },
  {
   "author": "柯文俊",
   "image_src": "Conocybe_tenera_6_CC BY-NC_柯文俊.jpg"
  },
  {
   "author": "柯文俊",
   "image_src": "Conocybe_tenera_2_CC BY-NC_柯文俊.jpg"
  },
  {
   "author": "柯文俊",
   "image_src": "Conocybe_tenera_3_CC BY-NC_柯文俊.jpg"
  },
  {
   "author": "柯文俊",
   "image_src": "Conocybe_tenera_4_CC BY-NC_柯文俊.jpg"
  },
  {
   "author": "柯文俊",
   "image_src": "Conocybe_tenera_5_CC BY-NC_柯文俊.jpg"
  },
  {
   "author": "柯文俊",
   "image_src": "Conocybe_tenera_1_CC BY-NC_柯文俊.jpg"
  }
 ],
 "names_zhcn": [
  "柔锥盖伞"
 ],
 "meta": {
  "CapColors": "4291605388",
  "CapDiamRangeValues": "30,50",
  "CapShape": "",
  "CapTexture": "",
  "CapMargin": "",
  "HymeniumType": "",
  "HymeniumColors": "",
  "HymeniumSporePrints": "",
  "HymeniumGillArrangement": "",
  "HymeniumGillAttachment": "",
  "HymeniumGillMarginate": "",
  "HymeniumPoresPerMM": "",
  "StalkAttachment": "",
  "StalkColors": "",
  "StalkTexture": "",
  "StalkHollow": "",
  "StalkPartialVeil": "",
  "StalkVolva": "",
  "StalkBase": "",
  "StalkDiamRangeValuess": "",
  "StalkLengthRangeValuess": "35,70",
  "Rareness": "",
  "Seasons": "",
  "GrowthType": "singly,scattered,grouped",
  "GrowthEnv": "ground,meadow",
  "Bruising": "",
  "Bioluminescent": "",
  "Edible": "",
  "Smell": "",
  "Taste": "",
  "LookAlikes": "",
  "Note": "",
  "GrowthEco": "saprotrophic"
 },
 "inaturalist": [
  {
   "name": "Conocybe tenera",
   "cname": "Common Conecap",
   "url": "https://www.inaturalist.org/taxa/121765-Conocybe-tenera",
   "src": "https://static.inaturalist.org/photos/5553532/thumb.jpeg"
  }
 ],
 "timestamp": "20241110-104108"
}