{
 "genus": "Strigula",
 "name": "elegans",
 "date": [
  "02/09/2024,6963414143768957",
  "02/08/2024,6954199304690441",
  "11/14/2020,3284170581693350"
 ],
 "names_zhtw": [
  "雅緻葉上衣"
 ],
 "names_en": [],
 "url": "3284170581693350",
 "images": [
  {
   "author": "陳雅芬",
   "image_src": "Strigula_elegans_1_CC BY-NC_陳雅芬.jpg"
  },
  {
   "author": "陳雅芬",
   "image_src": "Strigula_elegans_2_CC BY-NC_陳雅芬.jpg"
  },
  {
   "author": "陳雅芬",
   "image_src": "Strigula_elegans_3_CC BY-NC_陳雅芬.jpg"
  },
  {
   "author": "陳雅芬",
   "image_src": "Strigula_elegans_4_CC BY-NC_陳雅芬.jpg"
  },
  {
   "author": "陳雅芬",
   "image_src": "Strigula_elegans_5_CC BY-NC_陳雅芬.jpg"
  },
  {
   "author": "陳雅芬",
   "image_src": "Strigula_elegans_6_CC BY-NC_陳雅芬.jpg"
  },
  {
   "author": "陳雅芬",
   "image_src": "Strigula_elegans_7_CC BY-NC_陳雅芬.jpg"
  },
  {
   "author": "陳雅芬",
   "image_src": "Strigula_elegans_8_CC BY-NC_陳雅芬.jpg"
  },
  {
   "author": "陳雅芬",
   "image_src": "Strigula_elegans_9_CC BY-NC_陳雅芬.jpg"
  },
  {
   "author": "陳麗紅",
   "image_src": "Strigula_elegans_83bb7850-c687-11ee-9690-9f302a1423da_1.jpg"
  },
  {
   "author": "陳麗紅",
   "image_src": "Strigula_elegans_83bb7850-c687-11ee-9690-9f302a1423da_2.jpg"
  },
  {
   "author": "陳麗紅",
   "image_src": "Strigula_elegans_83bb7850-c687-11ee-9690-9f302a1423da_3.jpg"
  },
  {
   "author": "陳麗紅",
   "image_src": "Strigula_elegans_83bb7850-c687-11ee-9690-9f302a1423da_4.jpg"
  },
  {
   "author": "陳麗紅",
   "image_src": "Strigula_elegans_83bb7850-c687-11ee-9690-9f302a1423da_5.jpg"
  },
  {
   "author": "陳麗紅",
   "image_src": "Strigula_elegans_83bb7850-c687-11ee-9690-9f302a1423da_6.jpg"
  },
  {
   "author": "江志緯",
   "image_src": "Strigula_elegans_7a4853b0-c885-11ee-b545-b37d710e776e_1.jpg"
  },
  {
   "author": "江志緯",
   "image_src": "Strigula_elegans_7a4853b0-c885-11ee-b545-b37d710e776e_2.jpg"
  },
  {
   "author": "江志緯",
   "image_src": "Strigula_elegans_7a4853b0-c885-11ee-b545-b37d710e776e_3.jpg"
  },
  {
   "author": "江志緯",
   "image_src": "Strigula_elegans_7a4853b0-c885-11ee-b545-b37d710e776e_4.jpg"
  },
  {
   "author": "江志緯",
   "image_src": "Strigula_elegans_7a4853b0-c885-11ee-b545-b37d710e776e_5.jpg"
  },
  {
   "author": "江志緯",
   "image_src": "Strigula_elegans_7a4853b0-c885-11ee-b545-b37d710e776e_6.jpg"
  },
  {
   "author": "江志緯",
   "image_src": "Strigula_elegans_7a4853b0-c885-11ee-b545-b37d710e776e_7.jpg"
  },
  {
   "author": "江志緯",
   "image_src": "Strigula_elegans_7a4853b0-c885-11ee-b545-b37d710e776e_8.jpg"
  },
  {
   "author": "江志緯",
   "image_src": "Strigula_elegans_7a4853b0-c885-11ee-b545-b37d710e776e_9.jpg"
  },
  {
   "author": "江志緯",
   "image_src": "Strigula_elegans_7a4853b0-c885-11ee-b545-b37d710e776e_10.jpg"
  },
  {
   "author": "江志緯",
   "image_src": "Strigula_elegans_7a4853b0-c885-11ee-b545-b37d710e776e_11.jpg"
  }
 ],
 "names_zhcn": [
  "雅致叶上衣"
 ],
 "meta": {
  "CapColors": "4294309365,4278222848",
  "CapDiamRangeValues": "",
  "CapShape": "",
  "CapTexture": "",
  "CapMargin": "",
  "HymeniumType": "",
  "HymeniumColors": "",
  "HymeniumSporePrints": "",
  "HymeniumGillArrangement": "",
  "HymeniumGillAttachment": "",
  "HymeniumGillMarginate": "",
  "HymeniumPoresPerMM": "",
  "StalkAttachment": "",
  "StalkColors": "",
  "StalkTexture": "",
  "StalkHollow": "",
  "StalkPartialVeil": "",
  "StalkVolva": "",
  "StalkBase": "",
  "StalkDiamRangeValuess": "",
  "StalkLengthRangeValuess": "",
  "Rareness": "",
  "Seasons": "",
  "GrowthType": "",
  "GrowthEnv": "leaves",
  "Bruising": "",
  "Bioluminescent": "",
  "Edible": "",
  "Smell": "",
  "Taste": "",
  "LookAlikes": "",
  "Note": ""
 },
 "inaturalist": [
  {
   "name": "Strigula smaragdula",
   "cname": "Green Leaf Spots",
   "url": "https://www.inaturalist.org/taxa/352461-Strigula-smaragdula",
   "src": "https://inaturalist-open-data.s3.amazonaws.com/photos/25751000/thumb.jpg"
  }
 ],
 "timestamp": "20241006-170432"
}