{
 "genus": "Russula",
 "name": "azurea",
 "date": [
  "08/15/2022",
  "10/27/2021",
  "04/20/2021"
 ],
 "names_zhtw": [
  "葡紫紅菇"
 ],
 "names_en": [],
 "url": "4256876307756101",
 "images": [
  {
   "author": "Hannah Wang",
   "image_src": "Russula_azurea_2_CC BY-NC_Hannah Wang.jpg"
  },
  {
   "author": "Hannah Wang",
   "image_src": "Russula_azurea_5_CC BY-NC_Hannah Wang.jpg"
  },
  {
   "author": "Hannah Wang",
   "image_src": "Russula_azurea_3_CC BY-NC_Hannah Wang.jpg"
  },
  {
   "author": "Hannah Wang",
   "image_src": "Russula_azurea_4_CC BY-NC_Hannah Wang.jpg"
  },
  {
   "author": "Hannah Wang",
   "image_src": "Russula_azurea_1_CC BY-NC_Hannah Wang.jpg"
  },
  {
   "author": "Hannah Wang",
   "image_src": "Russula_azurea_6_CC BY-NC_Hannah Wang.jpg"
  },
  {
   "author": "Hannah Wang",
   "image_src": "Russula_azurea_7_CC BY-NC_Hannah Wang.jpg"
  },
  {
   "author": "Hannah Wang",
   "image_src": "Russula_azurea_8_CC BY-NC_Hannah Wang.jpg"
  },
  {
   "author": "陳雅芬",
   "image_src": "Russula_azurea_1_CC BY-NC_陳雅芬.jpg"
  },
  {
   "author": "陳雅芬",
   "image_src": "Russula_azurea_2_CC BY-NC_陳雅芬.jpg"
  },
  {
   "author": "陳雅芬",
   "image_src": "Russula_azurea_3_CC BY-NC_陳雅芬.jpg"
  },
  {
   "author": "陳雅芬",
   "image_src": "Russula_azurea_4_CC BY-NC_陳雅芬.jpg"
  },
  {
   "author": "陳雅芬",
   "image_src": "Russula_azurea_5_CC BY-NC_陳雅芬.jpg"
  },
  {
   "author": "陳雅芬",
   "image_src": "Russula_azurea_6_CC BY-NC_陳雅芬.jpg"
  },
  {
   "author": "James Ho",
   "image_src": "Russula_azurea_1_CC BY-NC_James Ho.jpg"
  },
  {
   "author": "James Ho",
   "image_src": "Russula_azurea_2_CC BY-NC_James Ho.jpg"
  },
  {
   "author": "James Ho",
   "image_src": "Russula_azurea_3_CC BY-NC_James Ho.jpg"
  },
  {
   "author": "James Ho",
   "image_src": "Russula_azurea_4_CC BY-NC_James Ho.jpg"
  },
  {
   "author": "James Ho",
   "image_src": "Russula_azurea_5_CC BY-NC_James Ho.jpg"
  },
  {
   "author": "James Ho",
   "image_src": "Russula_azurea_6_CC BY-NC_James Ho.jpg"
  },
  {
   "author": "James Ho",
   "image_src": "Russula_azurea_7_CC BY-NC_James Ho.jpg"
  },
  {
   "author": "James Ho",
   "image_src": "Russula_azurea_8_CC BY-NC_James Ho.jpg"
  },
  {
   "author": "James Ho",
   "image_src": "Russula_azurea_9_CC BY-NC_James Ho.jpg"
  },
  {
   "author": "James Ho",
   "image_src": "Russula_azurea_10_CC BY-NC_James Ho.jpg"
  }
 ],
 "names_zhcn": [
  "葡紫红菇"
 ],
 "meta": {
  "CapColors": "4287001761,4282843172,4283433144",
  "CapDiamRangeValues": "40,80",
  "CapShape": "",
  "CapTexture": "",
  "CapMargin": "",
  "HymeniumType": "gilled",
  "HymeniumColors": "",
  "HymeniumSporePrints": "",
  "HymeniumGillArrangement": "",
  "HymeniumGillAttachment": "",
  "HymeniumGillMarginate": "",
  "HymeniumPoresPerMM": "",
  "StalkAttachment": "",
  "StalkColors": "",
  "StalkTexture": "",
  "StalkHollow": "",
  "StalkPartialVeil": "none",
  "StalkVolva": "none",
  "StalkBase": "",
  "StalkDiamRangeValuess": "8,20",
  "StalkLengthRangeValuess": "30,70",
  "Rareness": "",
  "Seasons": "",
  "GrowthType": "",
  "GrowthEnv": "ground",
  "Bruising": "",
  "Bioluminescent": "",
  "Edible": "",
  "Smell": "",
  "Taste": "",
  "LookAlikes": "",
  "Note": "葡紫紅菇，種小名azurea意為「天藍色的」，指菌蓋帶藍紫色調。蓋藍紫至丁香紫、表面常被白色粉霜，菌褶白色，柄白而脆，肉脆味和，外生菌根生於針葉林（尤雲杉）林地。",
  "GrowthEco": "mycorrhizal"
 },
 "inaturalist": [
  {
   "name": "Russula azurea",
   "cname": "",
   "cname_zh": "葡紫紅菇",
   "url": "https://www.inaturalist.org/taxa/504136-Russula-azurea",
   "src": "https://inaturalist-open-data.s3.amazonaws.com/photos/111522936/thumb.jpg"
  }
 ],
 "timestamp": "20260718-230527"
}