{
 "name": "Endothia",
 "zhtw": "隱叢赤殼菌屬",
 "zhcn": "隐丛赤壳菌属",
 "timestamp": "20260722-215732",
 "list": [
  {
   "name": "Endothia gyrosa",
   "zhtw": "屈曲內座殼",
   "zhcn": "屈曲内座壳",
   "img": "Endothia_gyrosa_73844a30-63eb-11f1-be6c-2538eaf832fe_1.jpg"
  }
 ],
 "note": "隱叢赤殼菌屬隸屬子囊菌門糞殼菌綱（Sordariomycetes）間座殼目（Diaporthales）隱赤殼科（Cryphonectriaceae），為樹皮棲居的核菌類植物病原。其有性世代於寄主樹皮下形成橙紅至黃色的子座（stroma，色澤鮮明），內埋具長頸的子囊殼（perithecium）；子囊孢子無色、雙細胞。無性世代產生分生孢子器，溢出橙色孢子角。生態上為闊葉樹（尤殼斗科）樹皮的寄生菌，引起潰瘍與枝枯。歷史上著名的栗疫病（栗胴枯病）病原原置本屬而名 Endothia parasitica，曾於二十世紀摧毀北美的美洲栗，後依分子證據改隸隱赤殼屬（Cryphonectria parasitica）。本屬現存種如 Endothia gyrosa（櫟潰瘍病菌）。本屬以橙紅色子座與樹皮潰瘍病害著稱。"
}