{
 "genus": "Cyathus",
 "name": "magnomuralis",
 "date": [
  "01/01/0001"
 ],
 "names_zhtw": [
  "厚孢壁黑蛋巢菌"
 ],
 "names_en": [],
 "url": "1089503171160113",
 "images": [
  {
   "author": "陳雅芬",
   "image_src": "Cyathus_magnomuralis_1_CC BY-NC_陳雅芬.jpg"
  },
  {
   "author": "陳雅芬",
   "image_src": "Cyathus_magnomuralis_2_CC BY-NC_陳雅芬.jpg"
  },
  {
   "author": "陳雅芬",
   "image_src": "Cyathus_magnomuralis_3_CC BY-NC_陳雅芬.jpg"
  },
  {
   "author": "陳雅芬",
   "image_src": "Cyathus_magnomuralis_4_CC BY-NC_陳雅芬.jpg"
  },
  {
   "author": "陳雅芬",
   "image_src": "Cyathus_magnomuralis_5_CC BY-NC_陳雅芬.jpg"
  },
  {
   "author": "陳雅芬",
   "image_src": "Cyathus_magnomuralis_6_CC BY-NC_陳雅芬.jpg"
  }
 ],
 "names_zhcn": [
  "厚孢壁黑蛋巢菌"
 ],
 "meta": {
  "CapColors": "4278190080,4286141768",
  "CapDiamRangeValues": "4,6",
  "CapShape": "",
  "CapTexture": "",
  "CapMargin": "",
  "HymeniumType": "",
  "HymeniumColors": "",
  "HymeniumSporePrints": "",
  "HymeniumGillArrangement": "",
  "HymeniumGillAttachment": "",
  "HymeniumGillMarginate": "",
  "HymeniumPoresPerMM": "",
  "StalkAttachment": "",
  "StalkColors": "",
  "StalkTexture": "",
  "StalkHollow": "",
  "StalkPartialVeil": "",
  "StalkVolva": "",
  "StalkBase": "",
  "StalkDiamRangeValuess": "",
  "StalkLengthRangeValuess": "",
  "Rareness": "",
  "Seasons": "",
  "GrowthType": "grouped",
  "GrowthEnv": "wood",
  "Bruising": "",
  "Bioluminescent": "",
  "Edible": "",
  "Smell": "",
  "Taste": "",
  "LookAlikes": "",
  "Note": "高度5-6mm。",
  "GrowthEco": "saprotrophic"
 },
 "timestamp": "20240829-155325"
}